stock_mcp/__init__.py
stock_mcp/__main__.py
stock_mcp/app.py
stock_mcp/data_source_interface.py
stock_mcp/stock_data_source.py
stock_mcp/crawler/__init__.py
stock_mcp/crawler/base_crawler.py
stock_mcp/crawler/basic_data.py
stock_mcp/crawler/financial_analysis.py
stock_mcp/crawler/fundamental_data.py
stock_mcp/crawler/market.py
stock_mcp/crawler/real_time_data.py
stock_mcp/crawler/smart_review.py
stock_mcp/crawler/technical_data.py
stock_mcp/crawler/test.py
stock_mcp/crawler/test_count_changes.py
stock_mcp/crawler/valuation_data.py
stock_mcp/mcp_tools/__init__.py
stock_mcp/mcp_tools/financial_analysis.py
stock_mcp/mcp_tools/fundamental.py
stock_mcp/mcp_tools/kline_data.py
stock_mcp/mcp_tools/market.py
stock_mcp/mcp_tools/real_time_data.py
stock_mcp/mcp_tools/search.py
stock_mcp/mcp_tools/smart_review.py
stock_mcp/mcp_tools/valuation.py
stock_mcp/utils/__init__.py
stock_mcp/utils/markdown_formatter.py
stock_mcp/utils/utils.py
real_time_stock_mcp_service-1.2.1.dist-info/METADATA
real_time_stock_mcp_service-1.2.1.dist-info/WHEEL
real_time_stock_mcp_service-1.2.1.dist-info/entry_points.txt
real_time_stock_mcp_service-1.2.1.dist-info/licenses/LICENSE
real_time_stock_mcp_service-1.2.1.dist-info/RECORD
