Metadata-Version: 2.4
Name: real-time-stock-mcp-service
Version: 1.2.1
Summary: 一个获取实时股票数据服务和分析的MCP服务器
License-File: LICENSE
Requires-Python: >=3.12
Requires-Dist: mcp>=1.1.2
Requires-Dist: pandas>=2.2.0
Requires-Dist: python-dateutil>=2.9.0
Requires-Dist: requests>=2.32.0
